sentile/__init__.py
sentile/py.typed
sentile/s1/__init__.py
sentile/s1/filename.py
sentile/s1/tile.py
sentile/s2/__init__.py
sentile/s2/scl.py
sentile/s2/tile.py
sentile/scripts/__init__.py
sentile/scripts/__main__.py
sentile/scripts/s1.py
sentile/scripts/s2.py
sentile-1.2.0.dist-info/entry_points.txt
sentile-1.2.0.dist-info/LICENSE.md
sentile-1.2.0.dist-info/WHEEL
sentile-1.2.0.dist-info/METADATA
sentile-1.2.0.dist-info/RECORD
