Metadata-Version: 2.1
Name: sentile
Version: 1.2.0
Summary: Sentinel tile utilities
License: MIT
Author: Robofarm
Author-email: hello@robofarm.io
Requires-Python: >=3.8,<4.0
Classifier: License :: OSI Approved :: MIT License
Classifier: Programming Language :: Python :: 3
Classifier: Programming Language :: Python :: 3.8
Classifier: Programming Language :: Python :: 3.9
